[
  {
    "tipo": "agachamento",
    "timestamp": 1777978775.9010665,
    "timestamp_legivel": "2026-05-05T11:59:35.901067",
    "confianca": 0.4192003951591502,
    "frame_id": 6,
    "pessoa_id": null,
    "descricao": "Agachamento detectado por 5 frames",
    "dados": {
      "razao": 0.5807996048408498,
      "threshold": 0.6,
      "frames_agachado": 5
    }
  },
  {
    "tipo": "agachamento",
    "timestamp": 1777978776.169653,
    "timestamp_legivel": "2026-05-05T11:59:36.169653",
    "confianca": 0.4192003951591502,
    "frame_id": 7,
    "pessoa_id": null,
    "descricao": "Agachamento detectado por 6 frames",
    "dados": {
      "razao": 0.5807996048408498,
      "threshold": 0.6,
      "frames_agachado": 6
    }
  },
  {
    "tipo": "agachamento",
    "timestamp": 1777978776.1832106,
    "timestamp_legivel": "2026-05-05T11:59:36.183211",
    "confianca": 0.42020655333694745,
    "frame_id": 8,
    "pessoa_id": null,
    "descricao": "Agachamento detectado por 7 frames",
    "dados": {
      "razao": 0.5797934466630525,
      "threshold": 0.6,
      "frames_agachado": 7
    }
  },
  {
    "tipo": "agachamento",
    "timestamp": 1777978776.4494724,
    "timestamp_legivel": "2026-05-05T11:59:36.449472",
    "confianca": 0.42020655333694745,
    "frame_id": 9,
    "pessoa_id": null,
    "descricao": "Agachamento detectado por 8 frames",
    "dados": {
      "razao": 0.5797934466630525,
      "threshold": 0.6,
      "frames_agachado": 8
    }
  },
  {
    "tipo": "agachamento",
    "timestamp": 1777978776.4605124,
    "timestamp_legivel": "2026-05-05T11:59:36.460512",
    "confianca": 0.42095977564365616,
    "frame_id": 10,
    "pessoa_id": null,
    "descricao": "Agachamento detectado por 9 frames",
    "dados": {
      "razao": 0.5790402243563438,
      "threshold": 0.6,
      "frames_agachado": 9
    }
  },
  {
    "tipo": "agachamento",
    "timestamp": 1777978776.7785845,
    "timestamp_legivel": "2026-05-05T11:59:36.778584",
    "confianca": 0.42095977564365616,
    "frame_id": 11,
    "pessoa_id": null,
    "descricao": "Agachamento detectado por 10 frames",
    "dados": {
      "razao": 0.5790402243563438,
      "threshold": 0.6,
      "frames_agachado": 10
    }
  },
  {
    "tipo": "agachamento",
    "timestamp": 1777978776.788678,
    "timestamp_legivel": "2026-05-05T11:59:36.788678",
    "confianca": 0.42178699453952384,
    "frame_id": 12,
    "pessoa_id": null,
    "descricao": "Agachamento detectado por 11 frames",
    "dados": {
      "razao": 0.5782130054604762,
      "threshold": 0.6,
      "frames_agachado": 11
    }
  },
  {
    "tipo": "agachamento",
    "timestamp": 1777978777.065787,
    "timestamp_legivel": "2026-05-05T11:59:37.065787",
    "confianca": 0.42178699453952384,
    "frame_id": 13,
    "pessoa_id": null,
    "descricao": "Agachamento detectado por 12 frames",
    "dados": {
      "razao": 0.5782130054604762,
      "threshold": 0.6,
      "frames_agachado": 12
    }
  },
  {
    "tipo": "agachamento",
    "timestamp": 1777978777.0795496,
    "timestamp_legivel": "2026-05-05T11:59:37.079550",
    "confianca": 0.42219459112058344,
    "frame_id": 14,
    "pessoa_id": null,
    "descricao": "Agachamento detectado por 13 frames",
    "dados": {
      "razao": 0.5778054088794166,
      "threshold": 0.6,
      "frames_agachado": 13
    }
  },
  {
    "tipo": "agachamento",
    "timestamp": 1777978777.3940914,
    "timestamp_legivel": "2026-05-05T11:59:37.394091",
    "confianca": 0.42219459112058344,
    "frame_id": 15,
    "pessoa_id": null,
    "descricao": "Agachamento detectado por 14 frames",
    "dados": {
      "razao": 0.5778054088794166,
      "threshold": 0.6,
      "frames_agachado": 14
    }
  },
  {
    "tipo": "agachamento",
    "timestamp": 1777978777.4115407,
    "timestamp_legivel": "2026-05-05T11:59:37.411541",
    "confianca": 0.4216318873567394,
    "frame_id": 16,
    "pessoa_id": null,
    "descricao": "Agachamento detectado por 15 frames",
    "dados": {
      "razao": 0.5783681126432606,
      "threshold": 0.6,
      "frames_agachado": 15
    }
  },
  {
    "tipo": "agachamento",
    "timestamp": 1777978777.6613631,
    "timestamp_legivel": "2026-05-05T11:59:37.661363",
    "confianca": 0.4216318873567394,
    "frame_id": 17,
    "pessoa_id": null,
    "descricao": "Agachamento detectado por 16 frames",
    "dados": {
      "razao": 0.5783681126432606,
      "threshold": 0.6,
      "frames_agachado": 16
    }
  },
  {
    "tipo": "agachamento",
    "timestamp": 1777978777.6734226,
    "timestamp_legivel": "2026-05-05T11:59:37.673423",
    "confianca": 0.42014206210990745,
    "frame_id": 18,
    "pessoa_id": null,
    "descricao": "Agachamento detectado por 17 frames",
    "dados": {
      "razao": 0.5798579378900925,
      "threshold": 0.6,
      "frames_agachado": 17
    }
  },
  {
    "tipo": "agachamento",
    "timestamp": 1777978777.9950633,
    "timestamp_legivel": "2026-05-05T11:59:37.995063",
    "confianca": 0.42014206210990745,
    "frame_id": 19,
    "pessoa_id": null,
    "descricao": "Agachamento detectado por 18 frames",
    "dados": {
      "razao": 0.5798579378900925,
      "threshold": 0.6,
      "frames_agachado": 18
    }
  },
  {
    "tipo": "agachamento",
    "timestamp": 1777978778.0043607,
    "timestamp_legivel": "2026-05-05T11:59:38.004361",
    "confianca": 0.4187563880662726,
    "frame_id": 20,
    "pessoa_id": null,
    "descricao": "Agachamento detectado por 19 frames",
    "dados": {
      "razao": 0.5812436119337274,
      "threshold": 0.6,
      "frames_agachado": 19
    }
  },
  {
    "tipo": "agachamento",
    "timestamp": 1777978778.2559834,
    "timestamp_legivel": "2026-05-05T11:59:38.255983",
    "confianca": 0.4187563880662726,
    "frame_id": 21,
    "pessoa_id": null,
    "descricao": "Agachamento detectado por 20 frames",
    "dados": {
      "razao": 0.5812436119337274,
      "threshold": 0.6,
      "frames_agachado": 20
    }
  },
  {
    "tipo": "agachamento",
    "timestamp": 1777978778.2671754,
    "timestamp_legivel": "2026-05-05T11:59:38.267175",
    "confianca": 0.4175066822184229,
    "frame_id": 22,
    "pessoa_id": null,
    "descricao": "Agachamento detectado por 21 frames",
    "dados": {
      "razao": 0.5824933177815771,
      "threshold": 0.6,
      "frames_agachado": 21
    }
  },
  {
    "tipo": "agachamento",
    "timestamp": 1777978778.5555177,
    "timestamp_legivel": "2026-05-05T11:59:38.555518",
    "confianca": 0.4175066822184229,
    "frame_id": 23,
    "pessoa_id": null,
    "descricao": "Agachamento detectado por 22 frames",
    "dados": {
      "razao": 0.5824933177815771,
      "threshold": 0.6,
      "frames_agachado": 22
    }
  },
  {
    "tipo": "agachamento",
    "timestamp": 1777978778.5664208,
    "timestamp_legivel": "2026-05-05T11:59:38.566421",
    "confianca": 0.41622293515331854,
    "frame_id": 24,
    "pessoa_id": null,
    "descricao": "Agachamento detectado por 23 frames",
    "dados": {
      "razao": 0.5837770648466815,
      "threshold": 0.6,
      "frames_agachado": 23
    }
  },
  {
    "tipo": "agachamento",
    "timestamp": 1777978778.880007,
    "timestamp_legivel": "2026-05-05T11:59:38.880007",
    "confianca": 0.41622293515331854,
    "frame_id": 25,
    "pessoa_id": null,
    "descricao": "Agachamento detectado por 24 frames",
    "dados": {
      "razao": 0.5837770648466815,
      "threshold": 0.6,
      "frames_agachado": 24
    }
  },
  {
    "tipo": "agachamento",
    "timestamp": 1777978778.8922627,
    "timestamp_legivel": "2026-05-05T11:59:38.892263",
    "confianca": 0.41443963511940307,
    "frame_id": 26,
    "pessoa_id": null,
    "descricao": "Agachamento detectado por 25 frames",
    "dados": {
      "razao": 0.5855603648805969,
      "threshold": 0.6,
      "frames_agachado": 25
    }
  },
  {
    "tipo": "agachamento",
    "timestamp": 1777978779.1781428,
    "timestamp_legivel": "2026-05-05T11:59:39.178143",
    "confianca": 0.41443963511940307,
    "frame_id": 27,
    "pessoa_id": null,
    "descricao": "Agachamento detectado por 26 frames",
    "dados": {
      "razao": 0.5855603648805969,
      "threshold": 0.6,
      "frames_agachado": 26
    }
  },
  {
    "tipo": "agachamento",
    "timestamp": 1777978779.1906967,
    "timestamp_legivel": "2026-05-05T11:59:39.190697",
    "confianca": 0.41254629923716624,
    "frame_id": 28,
    "pessoa_id": null,
    "descricao": "Agachamento detectado por 27 frames",
    "dados": {
      "razao": 0.5874537007628338,
      "threshold": 0.6,
      "frames_agachado": 27
    }
  },
  {
    "tipo": "agachamento",
    "timestamp": 1777978779.4947255,
    "timestamp_legivel": "2026-05-05T11:59:39.494725",
    "confianca": 0.41254629923716624,
    "frame_id": 29,
    "pessoa_id": null,
    "descricao": "Agachamento detectado por 28 frames",
    "dados": {
      "razao": 0.5874537007628338,
      "threshold": 0.6,
      "frames_agachado": 28
    }
  },
  {
    "tipo": "agachamento",
    "timestamp": 1777978779.5148365,
    "timestamp_legivel": "2026-05-05T11:59:39.514837",
    "confianca": 0.41225436352452594,
    "frame_id": 30,
    "pessoa_id": null,
    "descricao": "Agachamento detectado por 29 frames",
    "dados": {
      "razao": 0.5877456364754741,
      "threshold": 0.6,
      "frames_agachado": 29
    }
  },
  {
    "tipo": "agachamento",
    "timestamp": 1777978779.882431,
    "timestamp_legivel": "2026-05-05T11:59:39.882431",
    "confianca": 0.41225436352452594,
    "frame_id": 31,
    "pessoa_id": null,
    "descricao": "Agachamento detectado por 30 frames",
    "dados": {
      "razao": 0.5877456364754741,
      "threshold": 0.6,
      "frames_agachado": 30
    }
  },
  {
    "tipo": "agachamento",
    "timestamp": 1777978779.8956985,
    "timestamp_legivel": "2026-05-05T11:59:39.895699",
    "confianca": 0.41337324933442965,
    "frame_id": 32,
    "pessoa_id": null,
    "descricao": "Agachamento detectado por 31 frames",
    "dados": {
      "razao": 0.5866267506655704,
      "threshold": 0.6,
      "frames_agachado": 31
    }
  },
  {
    "tipo": "agachamento",
    "timestamp": 1777978780.2363796,
    "timestamp_legivel": "2026-05-05T11:59:40.236380",
    "confianca": 0.41337324933442965,
    "frame_id": 33,
    "pessoa_id": null,
    "descricao": "Agachamento detectado por 32 frames",
    "dados": {
      "razao": 0.5866267506655704,
      "threshold": 0.6,
      "frames_agachado": 32
    }
  },
  {
    "tipo": "agachamento",
    "timestamp": 1777978780.2483418,
    "timestamp_legivel": "2026-05-05T11:59:40.248342",
    "confianca": 0.41625313650013085,
    "frame_id": 34,
    "pessoa_id": null,
    "descricao": "Agachamento detectado por 33 frames",
    "dados": {
      "razao": 0.5837468634998692,
      "threshold": 0.6,
      "frames_agachado": 33
    }
  },
  {
    "tipo": "agachamento",
    "timestamp": 1777978780.5720232,
    "timestamp_legivel": "2026-05-05T11:59:40.572023",
    "confianca": 0.41625313650013085,
    "frame_id": 35,
    "pessoa_id": null,
    "descricao": "Agachamento detectado por 34 frames",
    "dados": {
      "razao": 0.5837468634998692,
      "threshold": 0.6,
      "frames_agachado": 34
    }
  },
  {
    "tipo": "agachamento",
    "timestamp": 1777978780.5883322,
    "timestamp_legivel": "2026-05-05T11:59:40.588332",
    "confianca": 0.41643016572710145,
    "frame_id": 36,
    "pessoa_id": null,
    "descricao": "Agachamento detectado por 35 frames",
    "dados": {
      "razao": 0.5835698342728985,
      "threshold": 0.6,
      "frames_agachado": 35
    }
  },
  {
    "tipo": "agachamento",
    "timestamp": 1777978780.8396037,
    "timestamp_legivel": "2026-05-05T11:59:40.839604",
    "confianca": 0.41643016572710145,
    "frame_id": 37,
    "pessoa_id": null,
    "descricao": "Agachamento detectado por 36 frames",
    "dados": {
      "razao": 0.5835698342728985,
      "threshold": 0.6,
      "frames_agachado": 36
    }
  },
  {
    "tipo": "agachamento",
    "timestamp": 1777978780.8513563,
    "timestamp_legivel": "2026-05-05T11:59:40.851356",
    "confianca": 0.41751265631996826,
    "frame_id": 38,
    "pessoa_id": null,
    "descricao": "Agachamento detectado por 37 frames",
    "dados": {
      "razao": 0.5824873436800317,
      "threshold": 0.6,
      "frames_agachado": 37
    }
  },
  {
    "tipo": "agachamento",
    "timestamp": 1777978781.1744292,
    "timestamp_legivel": "2026-05-05T11:59:41.174429",
    "confianca": 0.41751265631996826,
    "frame_id": 39,
    "pessoa_id": null,
    "descricao": "Agachamento detectado por 38 frames",
    "dados": {
      "razao": 0.5824873436800317,
      "threshold": 0.6,
      "frames_agachado": 38
    }
  },
  {
    "tipo": "agachamento",
    "timestamp": 1777978781.185718,
    "timestamp_legivel": "2026-05-05T11:59:41.185718",
    "confianca": 0.41805902864758326,
    "frame_id": 40,
    "pessoa_id": null,
    "descricao": "Agachamento detectado por 39 frames",
    "dados": {
      "razao": 0.5819409713524167,
      "threshold": 0.6,
      "frames_agachado": 39
    }
  },
  {
    "tipo": "agachamento",
    "timestamp": 1777978781.5084414,
    "timestamp_legivel": "2026-05-05T11:59:41.508441",
    "confianca": 0.41805902864758326,
    "frame_id": 41,
    "pessoa_id": null,
    "descricao": "Agachamento detectado por 40 frames",
    "dados": {
      "razao": 0.5819409713524167,
      "threshold": 0.6,
      "frames_agachado": 40
    }
  },
  {
    "tipo": "agachamento",
    "timestamp": 1777978781.5215495,
    "timestamp_legivel": "2026-05-05T11:59:41.521549",
    "confianca": 0.41879697407413585,
    "frame_id": 42,
    "pessoa_id": null,
    "descricao": "Agachamento detectado por 41 frames",
    "dados": {
      "razao": 0.5812030259258641,
      "threshold": 0.6,
      "frames_agachado": 41
    }
  }
]